{
  "additionalNames": [
    "無力P",
    "Powerless",
    "DJ Powerless",
    "sts"
  ],
  "albumIds": [],
  "artistType": "Producer",
  "defaultName": "無力P",
  "descriptionShort": "",
  "displayName": "MuryokuP",
  "entityType": "artist",
  "externalLinks": [
    {
      "kind": "reference",
      "label": "MikuWiki",
      "official": true,
      "service": "www5.atwiki.jp",
      "url": "http://www5.atwiki.jp/hmiku/pages/10956.html"
    },
    {
      "kind": "official",
      "label": "Blog",
      "official": true,
      "service": "resonancesound.blogspot.com",
      "url": "http://resonancesound.blogspot.com/"
    },
    {
      "kind": "official",
      "label": "Piapro",
      "official": true,
      "service": "piapro.jp",
      "url": "http://piapro.jp/dreams3"
    },
    {
      "kind": "official",
      "label": "Twitter",
      "official": true,
      "service": "twitter.com",
      "url": "http://twitter.com/muryokup"
    },
    {
      "kind": "official",
      "label": "NND MyList",
      "official": true,
      "service": "nicovideo.jp",
      "url": "http://www.nicovideo.jp/mylist/14483709"
    },
    {
      "kind": "reference",
      "label": "Vocaloid Wiki",
      "official": true,
      "service": "vocaloid.wikia.com",
      "url": "http://vocaloid.wikia.com/wiki/Muryoku-P"
    },
    {
      "kind": "official",
      "label": "NND Account",
      "official": true,
      "service": "nicovideo.jp",
      "url": "http://www.nicovideo.jp/user/11701964"
    },
    {
      "kind": "official",
      "label": "SoundCloud",
      "official": true,
      "service": "soundcloud.com",
      "url": "https://soundcloud.com/powerless"
    },
    {
      "kind": "reference",
      "label": "VGMdb",
      "official": true,
      "service": "vgmdb.net",
      "url": "http://vgmdb.net/artist/13459"
    },
    {
      "kind": "reference",
      "label": "NicoNicoPedia",
      "official": true,
      "service": "dic.nicovideo.jp",
      "url": "http://dic.nicovideo.jp/a/%E7%84%A1%E5%8A%9Bp"
    },
    {
      "kind": "reference",
      "label": "UtaiteDB",
      "official": true,
      "service": "utaitedb.net",
      "url": "http://utaitedb.net/Ar/1270"
    },
    {
      "kind": "official",
      "label": "Tumblr",
      "official": true,
      "service": "powerlesssounds.tumblr.com",
      "url": "http://powerlesssounds.tumblr.com/"
    },
    {
      "kind": "official",
      "label": "Facebook",
      "official": true,
      "service": "facebook.com",
      "url": "https://www.facebook.com/pages/Powerless/297111870350860"
    },
    {
      "kind": "official",
      "label": "YouTube Channel (Old)",
      "official": true,
      "service": "youtube.com",
      "url": "https://www.youtube.com/channel/UC7SVTJPnwC4Cjn5bIKTXPZA"
    },
    {
      "kind": "reference",
      "label": "MusicBrainz (Powerless)",
      "official": true,
      "service": "musicbrainz.org",
      "url": "https://musicbrainz.org/artist/34cebbee-d6bc-486b-ae6b-f5bdef605055"
    },
    {
      "kind": "reference",
      "label": "MusicBrainz (無力P)",
      "official": true,
      "service": "musicbrainz.org",
      "url": "https://musicbrainz.org/artist/9e8b7442-4fa5-47a1-8924-a1b4fc1020cc"
    },
    {
      "kind": "official",
      "label": "Instagram",
      "official": true,
      "service": "instagram.com",
      "url": "https://www.instagram.com/powerless_/"
    },
    {
      "kind": "official",
      "label": "YouTube Channel (New)",
      "official": true,
      "service": "youtube.com",
      "url": "https://www.youtube.com/channel/UCIIJjephXPaMihtkDoWwMtw"
    },
    {
      "kind": "commercial",
      "label": "Spotify (Powerless)",
      "official": true,
      "service": "open.spotify.com",
      "url": "https://open.spotify.com/artist/5utxGGhcP0Xs2NMvLOvXqh?si=PuINtvYjRPC0xuzuuQon0Q&utm_source=copy-link"
    },
    {
      "kind": "commercial",
      "label": "Spotify (無力P)",
      "official": true,
      "service": "open.spotify.com",
      "url": "https://open.spotify.com/artist/5B7H1r9J5BDKdEr8Czhebo?si=z6fztI74Sm-Fwk-DHd9ZlQ&utm_source=copy-link"
    },
    {
      "kind": "commercial",
      "label": "Spotify (muryokup)",
      "official": true,
      "service": "open.spotify.com",
      "url": "https://open.spotify.com/artist/4vc8bLRr4cht2HGxP8c5KW?si=63X5-ivKQ2uHdVd08eIGuQ&utm_source=copy-link"
    },
    {
      "kind": "commercial",
      "label": "KARENT",
      "official": true,
      "service": "karent.jp",
      "url": "https://karent.jp/artist/pp000332"
    },
    {
      "kind": "commercial",
      "label": "TuneCore Japan",
      "official": true,
      "service": "tunecore.co.jp",
      "url": "https://www.tunecore.co.jp/artists/muryokup"
    },
    {
      "kind": "commercial",
      "label": "iTunes (JP)",
      "official": true,
      "service": "music.apple.com",
      "url": "https://music.apple.com/jp/artist/%E7%84%A1%E5%8A%9Bp/391730951"
    },
    {
      "kind": "commercial",
      "label": "iTunes",
      "official": true,
      "service": "music.apple.com",
      "url": "https://music.apple.com/in/artist/muryokup/391730951"
    },
    {
      "kind": "commercial",
      "label": "OTOTOY",
      "official": true,
      "service": "ototoy.jp",
      "url": "https://ototoy.jp/_/default/a/104416"
    },
    {
      "kind": "official",
      "label": "osu! Featured Artist Listing",
      "official": true,
      "service": "osu.ppy.sh",
      "url": "https://osu.ppy.sh/beatmaps/artists/120"
    },
    {
      "kind": "commercial",
      "label": "Bandcamp",
      "official": true,
      "service": "powerless.bandcamp.com",
      "url": "https://powerless.bandcamp.com/"
    }
  ],
  "groups": [
    "artist-520",
    "artist-5031",
    "artist-21336",
    "artist-276",
    "artist-3234",
    "artist-177526"
  ],
  "id": "artist-161",
  "name": "MuryokuP",
  "primaryImage": "https://static.vocadb.net/img/Artist/mainOrig/161.jpg?v=37",
  "rawHash": "cb18f46e1d57b1339d7c8324e0efcd088519bf174bf378e69611ef8b7f9dcd3d",
  "relatedArtistIds": [
    "artist-520",
    "artist-5031",
    "artist-21336",
    "artist-276",
    "artist-3234",
    "artist-177526"
  ],
  "slug": "muryokup--vocadb-161",
  "songIds": [],
  "source": "vocadb",
  "sourceUrl": "https://vocadb.net/Ar/161",
  "status": "active",
  "syncedAt": "2026-03-13T22:00:29.437Z",
  "upstreamUpdatedAt": null,
  "url": "/artists/muryokup--vocadb-161/",
  "vocadbId": 161,
  "voicebanks": []
}
